fujielab/audio/mcnr_input/__init__.py
fujielab/audio/mcnr_input/core.py
fujielab/audio/mcnr_input/process.py
fujielab/audio/mcnr_input/py.typed
fujielab/audio/mcnr_input/_backend/data.py
fujielab/audio/mcnr_input/_backend/input_capture.py
fujielab/audio/mcnr_input/_backend/input_capture_base.py
fujielab/audio/mcnr_input/_backend/input_capture_mac.py
fujielab/audio/mcnr_input/_backend/input_capture_soundcard_base.py
fujielab/audio/mcnr_input/_backend/input_capture_win.py
fujielab/audio/mcnr_input/_backend/output_capture.py
fujielab/audio/mcnr_input/_backend/output_capture_base.py
fujielab/audio/mcnr_input/_backend/output_capture_mac.py
fujielab/audio/mcnr_input/_backend/output_capture_win.py
fujielab_audio_mcnr_input-0.1.1.dist-info/licenses/LICENSE
fujielab_audio_mcnr_input-0.1.1.dist-info/METADATA
fujielab_audio_mcnr_input-0.1.1.dist-info/WHEEL
fujielab_audio_mcnr_input-0.1.1.dist-info/top_level.txt
fujielab_audio_mcnr_input-0.1.1.dist-info/RECORD
