Metadata-Version: 2.4
Name: fujielab-audio-mcnr_input
Version: 0.1.1
Summary: Multi channel noise reduction based echo cancelling audio input stream
Author: Shinya Fujie
License: MIT
Project-URL: Homepage, https://github.com/fujielab/fujielab-audio-mcnr_input
Project-URL: Repository, https://github.com/fujielab/fujielab-audio-mcnr_input
Project-URL: Issues, https://github.com/fujielab/fujielab-audio-mcnr_input/issues
Project-URL: Documentation, https://github.com/fujielab/fujielab-audio-mcnr_input#readme
Project-URL: Changelog, https://github.com/fujielab/fujielab-audio-mcnr_input/blob/main/CHANGELOG.md
Keywords: audio,noise-reduction,echo-cancellation,sound-processing,real-time-audio,multi-channel
Classifier: Development Status :: 4 - Beta
Classifier: Intended Audience :: Developers
Classifier: Intended Audience :: Science/Research
Classifier: Operating System :: OS Independent
Classifier: Programming Language :: Python :: 3
Classifier: Programming Language :: Python :: 3.8
Classifier: Programming Language :: Python :: 3.9
Classifier: Programming Language :: Python :: 3.10
Classifier: Programming Language :: Python :: 3.11
Classifier: Programming Language :: Python :: 3.12
Classifier: Topic :: Multimedia :: Sound/Audio
Classifier: Topic :: Multimedia :: Sound/Audio :: Capture/Recording
Classifier: Topic :: Scientific/Engineering :: Artificial Intelligence
Requires-Python: >=3.8
License-File: LICENSE
Requires-Dist: numpy>=1.20.0
Requires-Dist: sounddevice>=0.4.0
Requires-Dist: soundfile>=0.10.0
Requires-Dist: soundcard>=0.4.0
Requires-Dist: scipy>=1.0
Requires-Dist: pywin32>=227; sys_platform == "win32"
Provides-Extra: dev
Requires-Dist: pytest>=6.0; extra == "dev"
Requires-Dist: pytest-cov; extra == "dev"
Requires-Dist: black; extra == "dev"
Requires-Dist: flake8; extra == "dev"
Requires-Dist: mypy; extra == "dev"
Provides-Extra: docs
Requires-Dist: sphinx; extra == "docs"
Requires-Dist: sphinx-rtd-theme; extra == "docs"
Dynamic: license-file
